save_excel/__init__.py
save_excel/save_excel.py
save_excel/config/__init__.py
save_excel/config/functionalities.py
save_excel/config/properties.py
save_excel/config/styles.py
save_excel/dictionary/__init__.py
save_excel/dictionary/builder.py
save_excel/dictionary/structures.py
save_excel/dxf/__init__.py
save_excel/dxf/dxf.py
save_excel/layout/__init__.py
save_excel/layout/cell_range.py
save_excel/layout/layout.py
save_excel/utils/__init__.py
save_excel/utils/alphabet.py
save_excel/utils/cell.py
save_excel/utils/sequence.py
save_excel/utils/utils.py
save_excel/utils/vectorization.py
save_excel-0.1.2.dist-info/METADATA
save_excel-0.1.2.dist-info/WHEEL
save_excel-0.1.2.dist-info/top_level.txt
save_excel-0.1.2.dist-info/RECORD
